talonfmt/__init__.py
talonfmt/_compat_ast.py
talonfmt/_compat_singledispatchmethod.py
talonfmt/_compat_singledispatchmethod.pyi
talonfmt/cli.py
talonfmt/editorconfig.py
talonfmt/formatter.py
talonfmt/py.typed
talonfmt-1.10.2.dist-info/LICENSE
talonfmt-1.10.2.dist-info/METADATA
talonfmt-1.10.2.dist-info/WHEEL
talonfmt-1.10.2.dist-info/entry_points.txt
talonfmt-1.10.2.dist-info/top_level.txt
talonfmt-1.10.2.dist-info/RECORD
