Metadata-Version: 2.1
Name: talonfmt
Version: 1.10.2
Summary: A code formatter for Talon files
Author-email: Wen Kokke <wenkokke@users.noreply.github.com>
License: MIT License
Keywords: talon,formatter
Classifier: License :: OSI Approved :: MIT License
Classifier: Topic :: Software Development :: Compilers
Classifier: Programming Language :: Python :: 3 :: Only
Classifier: Programming Language :: Python :: 3
Classifier: Programming Language :: Python :: 3.9
Classifier: Programming Language :: Python :: 3.10
Classifier: Programming Language :: Python :: 3.11
Classifier: Programming Language :: Python :: 3.12
Requires-Python: <3.13,>=3.9
License-File: LICENSE
Requires-Dist: click <9,>=8.1.3
Requires-Dist: dataclasses-json <0.7,>=0.5.7
Requires-Dist: doc-printer <0.16,>=0.13.1
Requires-Dist: editorconfig <0.13,>=0.12.3
Requires-Dist: tree-sitter-talon <3!2,>=3!1.7
Requires-Dist: singledispatchmethod <2,>=1.0 ; python_version < "3.8"
Requires-Dist: astunparse <2,>=1.6.3 ; python_version < "3.9"
Provides-Extra: mypy
Requires-Dist: types-setuptools ; extra == 'mypy'
Provides-Extra: test
Requires-Dist: bumpver ; extra == 'test'
Requires-Dist: mypy <2,>=1.1.1 ; extra == 'test'
Requires-Dist: pytest <9,>=7.1.2 ; extra == 'test'
Requires-Dist: pytest-golden <0.3,>=0.2.2 ; extra == 'test'
Requires-Dist: pytest-benchmark <5.0.0,>=3.4.1 ; extra == 'test'
